LICENSE
MANIFEST.in
README.rst
setup.cfg
setup.py
django_rest_framework_apikeys/__init__.py
django_rest_framework_apikeys/admin.py
django_rest_framework_apikeys/apps.py
django_rest_framework_apikeys/authentication.py
django_rest_framework_apikeys/models.py
django_rest_framework_apikeys/serializers.py
django_rest_framework_apikeys/urls.py
django_rest_framework_apikeys/views.py
django_rest_framework_apikeys.egg-info/PKG-INFO
django_rest_framework_apikeys.egg-info/SOURCES.txt
django_rest_framework_apikeys.egg-info/dependency_links.txt
django_rest_framework_apikeys.egg-info/top_level.txt
django_rest_framework_apikeys/migrations/0001_initial.py
django_rest_framework_apikeys/migrations/0002_auto_20180225_1912.py
django_rest_framework_apikeys/migrations/__init__.py