Metadata-Version: 1.1
Name: django-rest-framework-apikeys
Version: 0.1
Summary: django-rest-framework-apikeys allows you to Authenticate your REST api with api keys on a per user basis.
Home-page: https://github.com/DannyAziz/django-rest-framework-apikeys
Author: DannyAziz
Author-email: UNKNOWN
License: MIT License
Download-URL: https://github.com/DannyAziz/django-rest-framework-apikeys/archive/0.1.tar.gz
Platform: UNKNOWN
Classifier: Environment :: Web Environment
Classifier: Framework :: Django
Classifier: Framework :: Django :: 1.11
Classifier: Intended Audience :: Developers
Classifier: License :: OSI Approved :: MIT License
Classifier: Operating System :: OS Independent
Classifier: Programming Language :: Python
Classifier: Programming Language :: Python :: 2.7
Classifier: Topic :: Internet :: WWW/HTTP
Classifier: Topic :: Internet :: WWW/HTTP :: Dynamic Content
